Metadata-Version: 1.1
Name: pymake2
Version: 0.5.33
Summary: pymake2 is a simple Python-based make system. It brings simplicity and flexibility of Python language to makefiles.
Home-page: https://bitbucket.org/saudalwasly/pymake2/src
Author: Saud Wasly
Author-email: saudalwasli@gmail.com
License: MIT
Keywords: make makefile build
Platform: UNKNOWN
Classifier: Development Status :: 4 - Beta
Classifier: Topic :: Utilities
Classifier: License :: OSI Approved :: MIT License
